apgmx/__init__.py
apgmx/config_loader.py
apgmx/launcher.py
apgmx/migration.py
apgmx/revision.py
apgmx/utils.py
apgmx-0.0.1.dist-info/LICENSE.txt
apgmx-0.0.1.dist-info/METADATA
apgmx-0.0.1.dist-info/WHEEL
apgmx-0.0.1.dist-info/entry_points.txt
apgmx-0.0.1.dist-info/RECORD
