Metadata-Version: 2.1
Name: apgmx
Version: 0.0.1
Summary: A database migrations tool for asyncpg
License: GPL-3.0
Author: Noelle
Author-email: 73260931+No767@users.noreply.github.com
Requires-Python: >=3.8,<4.0
Classifier: License :: OSI Approved :: GNU General Public License v3 (GPLv3)
Classifier: Programming Language :: Python :: 3
Classifier: Programming Language :: Python :: 3.8
Classifier: Programming Language :: Python :: 3.9
Classifier: Programming Language :: Python :: 3.10
Classifier: Programming Language :: Python :: 3.11
Provides-Extra: uvloop
Requires-Dist: asyncpg (>=0.27.0,<0.28.0)
Requires-Dist: typer[all] (>=0.9.0,<0.10.0)
Requires-Dist: uvloop (>=0.17.0,<0.18.0) ; extra == "uvloop"
